{
  "resourceType": "Provenance",
  "id": "ProvenanceCondition111",
  "target": [
    {
      "reference": "Condition/Condition111"
    }
  ],
  "recorded": "2020-03-17T10:09:27+01:00",
  "agent": [
    {
      "type": {
        "coding": [
          {
            "code": "legal"
          }
        ]
      },
      "who": {
        "reference": "Practitioner/7777777"
      }
    }
  ],
  "reason": [
    {
      "coding": [
        {
          "system": "http://terminology.hl7.org/CodeSystem/v3-ActReason",
          "code": "TREAT"
        }
      ]
    }
  ]
}
